pterodactyl_exporter/__init__.py
pterodactyl_exporter/config_load.py
pterodactyl_exporter/http_client.py
pterodactyl_exporter/http_server.py
pterodactyl_exporter/pterodactyl_exporter.py
pterodactyl_exporter/dto/__init__.py
pterodactyl_exporter/dto/config.py
pterodactyl_exporter/dto/metrics.py
pterodactyl_exporter/dto/validation.py
pterodactyl_exporter/enum/__init__.py
pterodactyl_exporter/enum/server_list_type.py
pterodactyl_exporter/tests/__init__.py
pterodactyl_exporter/tests/test_config_load.py
pterodactyl_exporter/tests/test_http_client.py
pterodactyl_exporter/tests/test_http_server.py
pterodactyl_exporter/tests/dto/__init__.py
pterodactyl_exporter/tests/dto/test_config.py
pterodactyl_exporter-1.0.6.post1.dist-info/licenses/LICENSE.md
pterodactyl_exporter-1.0.6.post1.dist-info/METADATA
pterodactyl_exporter-1.0.6.post1.dist-info/WHEEL
pterodactyl_exporter-1.0.6.post1.dist-info/entry_points.txt
pterodactyl_exporter-1.0.6.post1.dist-info/top_level.txt
pterodactyl_exporter-1.0.6.post1.dist-info/RECORD
