Metadata-Version: 2.4
Name: pterodactyl_exporter
Version: 1.0.6.post1
Summary: Metrics exporter for Pterodactyl
Author-email: LOENS23 <info@loens2.com>
License-Expression: GPL-3.0
Project-URL: Homepage, https://github.com/LOENS2/pterodactyl_exporter
Requires-Python: >=3.8
License-File: LICENSE.md
Requires-Dist: PyYAML~=6.0.1
Requires-Dist: setuptools~=80.9.0
Requires-Dist: python-dateutil~=2.9.0.post0
Requires-Dist: prometheus_client~=0.22.0
Requires-Dist: dataclasses_json~=0.6.4
Requires-Dist: requests~=2.31
Provides-Extra: test
Requires-Dist: pytest>=7.0; extra == "test"
Dynamic: license-file
